MANIFEST.in
README.rst
setup.py
doc/Makefile
doc/build_instrument_method_map.py
doc/build_plugin_docs.py
doc/make.bat
doc/requirements.txt
doc/source/WA-logo-white.svg
doc/source/api.rst
doc/source/changes.rst
doc/source/conf.py
doc/source/developer_information.rst
doc/source/faq.rst
doc/source/glossary.rst
doc/source/index.rst
doc/source/instrument_method_map.template
doc/source/migration_guide.rst
doc/source/plugins.rst
doc/source/user_information.rst
doc/source/api/output.rst
doc/source/api/workload.rst
doc/source/developer_information/developer_guide.rst
doc/source/developer_information/developer_reference.rst
doc/source/developer_information/how_to.rst
doc/source/developer_information/developer_guide/writing_plugins.rst
doc/source/developer_information/developer_reference/WA_Execution.svg
doc/source/developer_information/developer_reference/WA_Signal_Dispatch.svg
doc/source/developer_information/developer_reference/contributing.rst
doc/source/developer_information/developer_reference/framework_overview.rst
doc/source/developer_information/developer_reference/plugins.rst
doc/source/developer_information/developer_reference/revent.rst
doc/source/developer_information/developer_reference/serialization.rst
doc/source/developer_information/how_tos/adding_plugins.rst
doc/source/developer_information/how_tos/processing_output.rst
doc/source/user_information/how_to.rst
doc/source/user_information/installation.rst
doc/source/user_information/user_guide.rst
doc/source/user_information/user_reference.rst
doc/source/user_information/how_tos/agenda.rst
doc/source/user_information/how_tos/device_setup.rst
doc/source/user_information/how_tos/revent.rst
doc/source/user_information/user_reference/agenda.rst
doc/source/user_information/user_reference/configuration.rst
doc/source/user_information/user_reference/invocation.rst
doc/source/user_information/user_reference/output_directory.rst
doc/source/user_information/user_reference/runtime_parameters.rst
scripts/cpustates
wlauto.egg-info/PKG-INFO
wlauto.egg-info/SOURCES.txt
wlauto.egg-info/dependency_links.txt
wlauto.egg-info/requires.txt
wlauto.egg-info/top_level.txt