Metadata-Version: 2.1
Name: wlauto
Version: 3.3.1
Summary: A framework for automating workload execution and measurement collection on ARM devices.
Home-page: https://github.com/ARM-software/workload-automation
Maintainer: ARM Architecture & Technology Device Lab
Maintainer-email: workload-automation@arm.com
License: Apache v2
Platform: UNKNOWN
Classifier: Development Status :: 5 - Production/Stable
Classifier: Environment :: Console
Classifier: License :: OSI Approved :: Apache Software License
Classifier: Operating System :: POSIX :: Linux
Classifier: Programming Language :: Python :: 3
Provides-Extra: all
Provides-Extra: daq
Provides-Extra: doc
Provides-Extra: notify
Provides-Extra: postgres
Provides-Extra: test
